pi/__init__.py
pi_calculater-2024.11.1.dist-info/LICENSE
pi_calculater-2024.11.1.dist-info/METADATA
pi_calculater-2024.11.1.dist-info/WHEEL
pi_calculater-2024.11.1.dist-info/top_level.txt
pi_calculater-2024.11.1.dist-info/RECORD
