Metadata-Version: 2.1
Name: pi_calculater
Version: 2024.11.1
Summary: 计算π的库
Author: LightingLong
Author-email: 17818883308@139.com
Classifier: Programming Language :: Python :: 3
Classifier: License :: OSI Approved :: MIT License
Classifier: Operating System :: OS Independent
Requires-Python: >=3.9
License-File: LICENSE
